mccetools/__init__.py
mccetools/cli.py
mccetools/core.py
pdbtools/__init__.py
pdbtools/cli.py
pdbtools/core.py
pymcce/__init__.py
pymcce/cli.py
pymcce/constants.py
pymcce/core.py
pymcce/mcce.py
pymcce/utils.py
pymcce/data/ftpl/BCT_OG.ftpl
pymcce/data/ftpl/CHL_QMhybrid_head+dipole.ftpl
pymcce/data/ftpl/CT1_QMhybrid_tail.ftpl
pymcce/data/ftpl/CT2_QMhybrid_tail.ftpl
pymcce/data/ftpl/CT3_QMhybrid_tail.ftpl
pymcce/data/ftpl/CT4_QMhybrid_tail.ftpl
pymcce/data/ftpl/DGD_GR.ftpl
pymcce/data/ftpl/FME_GR.ftpl
pymcce/data/ftpl/PHO_GR.ftpl
pymcce/data/ftpl/PL9_OGedit.ftpl
pymcce/data/ftpl/SQD_GR.ftpl
pymcce/data/ftpl/_K_.ftpl
pymcce/data/ftpl/_ca.ftpl
pymcce/data/ftpl/_cl.ftpl
pymcce/data/ftpl/_mg.ftpl
pymcce/data/ftpl/_na.ftpl
pymcce/data/ftpl/_zn.ftpl
pymcce/data/ftpl/ala.ftpl
pymcce/data/ftpl/arg.ftpl
pymcce/data/ftpl/asn.ftpl
pymcce/data/ftpl/asp.ftpl
pymcce/data/ftpl/bcr.ftpl
pymcce/data/ftpl/ctr.ftpl
pymcce/data/ftpl/cyd.ftpl
pymcce/data/ftpl/cyl.ftpl
pymcce/data/ftpl/cys.ftpl
pymcce/data/ftpl/extra.ftpl
pymcce/data/ftpl/fe2_OG.ftpl
pymcce/data/ftpl/gln.ftpl
pymcce/data/ftpl/glu.ftpl
pymcce/data/ftpl/gly.ftpl
pymcce/data/ftpl/gol_GR.ftpl
pymcce/data/ftpl/hem_OG.ftpl
pymcce/data/ftpl/hil.ftpl
pymcce/data/ftpl/his.ftpl
pymcce/data/ftpl/hoh.ftpl
pymcce/data/ftpl/ile.ftpl
pymcce/data/ftpl/leu.ftpl
pymcce/data/ftpl/ligand_detect_rules.ftpl
pymcce/data/ftpl/loose_cofactors.ftpl
pymcce/data/ftpl/lys.ftpl
pymcce/data/ftpl/mel.ftpl
pymcce/data/ftpl/mem.ftpl
pymcce/data/ftpl/met.ftpl
pymcce/data/ftpl/no3.ftpl
pymcce/data/ftpl/ntg.ftpl
pymcce/data/ftpl/ntr.ftpl
pymcce/data/ftpl/oeh.ftpl
pymcce/data/ftpl/paa_OG.ftpl
pymcce/data/ftpl/pdd_OG.ftpl
pymcce/data/ftpl/phe.ftpl
pymcce/data/ftpl/pro.ftpl
pymcce/data/ftpl/ser.ftpl
pymcce/data/ftpl/thr.ftpl
pymcce/data/ftpl/trp.ftpl
pymcce/data/ftpl/tyr.ftpl
pymcce/data/ftpl/val.ftpl
pymcce/data/prm/rename.txt
pymcce/data/prm/rotamer_level1.prm
pymcce/data/prm/rotamer_level2.prm
pymcce/data/prm/rotamer_level3.prm
pymcce/data/prm/run.prm.default
pymcce-0.2.0.dist-info/licenses/LICENSE
pymcce-0.2.0.dist-info/METADATA
pymcce-0.2.0.dist-info/WHEEL
pymcce-0.2.0.dist-info/entry_points.txt
pymcce-0.2.0.dist-info/top_level.txt
pymcce-0.2.0.dist-info/RECORD
