Metadata-Version: 2.4
Name: pymcce
Version: 0.2.0
Summary: Python implementation of core functions from Gunner Lab's MCCE
Author-email: Junjun Mao <junjun.mao@gmail.com>
License: MIT License
Project-URL: Homepage, https://github.com/newbooks/PyMCCE
Project-URL: Bug Tracker, https://github.com/newbooks/PyMCCE/issues
Project-URL: Documentation, https://github.com/newbooks/PyMCCE#readme
Project-URL: Source Code, https://github.com/newbooks/PyMCCE
Keywords: molecular dynamics,continuum,electrostatics,computational chemistry,mcce
Classifier: Development Status :: 3 - Alpha
Classifier: Intended Audience :: Science/Research
Classifier: License :: OSI Approved :: MIT License
Classifier: Programming Language :: Python :: 3
Classifier: Programming Language :: Python :: 3.12
Classifier: Programming Language :: Python :: 3.13
Classifier: Programming Language :: Python :: 3.14
Classifier: Topic :: Scientific/Engineering :: Bio-Informatics
Classifier: Topic :: Scientific/Engineering :: Physics
Requires-Python: >=3.12
License-File: LICENSE
Requires-Dist: numpy
Requires-Dist: scipy
Requires-Dist: typer
Requires-Dist: numba
Requires-Dist: requests
Requires-Dist: rich
Provides-Extra: docs
Requires-Dist: sphinx>=4.0; extra == "docs"
Requires-Dist: sphinx-rtd-theme; extra == "docs"
Requires-Dist: myst-parser; extra == "docs"
Provides-Extra: dev
Requires-Dist: pytest>=7.0; extra == "dev"
Requires-Dist: pytest-cov; extra == "dev"
Requires-Dist: black; extra == "dev"
Requires-Dist: ruff; extra == "dev"
Requires-Dist: mypy; extra == "dev"
Dynamic: license-file
